Workbook

Sheet Main
C1: Change Me ↓ | E1: Change Me ↓ | G1: Change Me ↓ | I1: Change Me ↓
B2: Units | C2: Per Hectare | D2: =if($C$2="Per Acre","Num Acres","Num Hectares") -> Num Hectares | E2: 1 | F2: Yield Bonus | G2: 0.425 | H2: Sell Price | I2: Max Seasonal
B4: Crop Income | I4: Forager Income
B6: NAME | C6: EASY | D6: NORMAL | E6: HARD | F6: M³ | G6: TONS | I6: NAME | J6: EASY | K6: NORMAL | L6: HARD | M6: M³ | N6: TONS
B7: Barley | C7: =product(E7,3) -> 15543.079 | D7: =product(E7,1.8) -> 9325.8475 | E7: =product('Crop Data'!B2,'Crop Data'!C2,if($I$2="Baseline",1,'Crop Data'!D2),$E$2,Variables!$B$2,Variables!$B$3) -> 5181.0264 | F7: =product(product('Crop Data'!B2,$E$2,Variables!$B$2,Variables!$B$3),0.001) -> 13.68 | G7: =product(F7,'Crop Data'!F2) -> 9.3024 | I7: Barley Silage | J7: =product(L7,3) -> 19863.36 | K7: =product(L7,1.8) -> 11918.016 | L7: =product('Silage Data'!B2,'Silage Data'!C2,$E$2,Variables!$B$2,Variables!$B$3,Variables!$B$4) -> 6621.12 | M7: =product(product('Silage Data'!B2,'Silage Data'!C2,$E$2,Variables!$B$2,Variables!$B$3),0.001) -> 54.72 | N7: =product(M7,Variables!$B$5) -> 16.416
B8: Beet Root | C8: =product(E8,3) -> 34667.429 | D8: =product(E8,1.8) -> 20800.457 | E8: =product('Crop Data'!B3,'Crop Data'!C3,if($I$2="Baseline",1,'Crop Data'!D3),$E$2,Variables!$B$2,Variables!$B$3) -> 11555.809 | F8: =product(product('Crop Data'!B3,$E$2,Variables!$B$2,Variables!$B$3),0.001) -> 82.365 | G8: =product(F8,'Crop Data'!F3) -> 42.8298 | I8: Canola Silage | J8: =product(L8,3) -> 12000.78 | K8: =product(L8,1.8) -> 7200.468 | L8: =product('Silage Data'!B3,'Silage Data'!C3,$E$2,Variables!$B$2,Variables!$B$3,Variables!$B$4) -> 4000.26 | M8: =product(product('Silage Data'!B3,'Silage Data'!C3,$E$2,Variables!$B$2,Variables!$B$3),0.001) -> 33.06 | N8: =product(M8,Variables!$B$5) -> 9.918
B9: Canola | C9: =product(E9,3) -> 18091.176 | D9: =product(E9,1.8) -> 10854.706 | E9: =product('Crop Data'!B4,'Crop Data'!C4,if($I$2="Baseline",1,'Crop Data'!D4),$E$2,Variables!$B$2,Variables!$B$3) -> 6030.392 | F9: =product(product('Crop Data'!B4,$E$2,Variables!$B$2,Variables!$B$3),0.001) -> 8.265 | G9: =product(F9,'Crop Data'!F4) -> 4.959 | I9: Corn Silage | J9: =product(L9,3) -> 37119.654 | K9: =product(L9,1.8) -> 22271.792 | L9: =product('Silage Data'!B4,'Silage Data'!C4,$E$2,Variables!$B$2,Variables!$B$3,Variables!$B$4) -> 12373.218 | M9: =product(product('Silage Data'!B4,'Silage Data'!C4,$E$2,Variables!$B$2,Variables!$B$3),0.001) -> 102.258 | N9: =product(M9,Variables!$B$5) -> 30.6774
B10: Carrot | C10: =product(E10,3) -> 49968.765 | D10: =product(E10,1.8) -> 29981.259 | E10: =product('Crop Data'!B5,'Crop Data'!C5,if($I$2="Baseline",1,'Crop Data'!D5),$E$2,Variables!$B$2,Variables!$B$3) -> 16656.255 | F10: =product(product('Crop Data'!B5,$E$2,Variables!$B$2,Variables!$B$3),0.001) -> 109.725 | G10: =product(F10,'Crop Data'!F5) -> 70.224 | I10: Oat Silage | J10: =product(L10,3) -> 11793.87 | K10: =product(L10,1.8) -> 7076.322 | L10: =product('Silage Data'!B5,'Silage Data'!C5,$E$2,Variables!$B$2,Variables!$B$3,Variables!$B$4) -> 3931.29 | M10: =product(product('Silage Data'!B5,'Silage Data'!C5,$E$2,Variables!$B$2,Variables!$B$3),0.001) -> 32.49 | N10: =product(M10,Variables!$B$5) -> 9.747
B11: Corn | C11: =product(E11,3) -> 19877.382 | D11: =product(E11,1.8) -> 11926.429 | E11: =product('Crop Data'!B6,'Crop Data'!C6,if($I$2="Baseline",1,'Crop Data'!D6),$E$2,Variables!$B$2,Variables!$B$3) -> 6625.794 | F11: =product(product('Crop Data'!B6,$E$2,Variables!$B$2,Variables!$B$3),0.001) -> 13.11 | G11: =product(F11,'Crop Data'!F6) -> 10.488 | I11: Sorghum Silage | J11: =product(L11,3) -> 16966.62 | K11: =product(L11,1.8) -> 10179.972 | L11: =product('Silage Data'!B6,'Silage Data'!C6,$E$2,Variables!$B$2,Variables!$B$3,Variables!$B$4) -> 5655.54 | M11: =product(product('Silage Data'!B6,'Silage Data'!C6,$E$2,Variables!$B$2,Variables!$B$3),0.001) -> 46.74 | N11: =product(M11,Variables!$B$5) -> 14.022
B12: Cotton | C12: =product(E12,3) -> 29527.033 | D12: =product(E12,1.8) -> 17716.22 | E12: =product('Crop Data'!B7,'Crop Data'!C7,if($I$2="Baseline",1,'Crop Data'!D7),$E$2,Variables!$B$2,Variables!$B$3) -> 9842.3445 | F12: =product(product('Crop Data'!B7,$E$2,Variables!$B$2,Variables!$B$3),0.001) -> 7.08225 | G12: =product(F12,'Crop Data'!F7) -> 1.6289175 | I12: Soybean Silage | J12: =product(L12,3) -> 9310.95 | K12: =product(L12,1.8) -> 5586.57 | L12: =product('Silage Data'!B7,'Silage Data'!C7,$E$2,Variables!$B$2,Variables!$B$3,Variables!$B$4) -> 3103.65 | M12: =product(product('Silage Data'!B7,'Silage Data'!C7,$E$2,Variables!$B$2,Variables!$B$3),0.001) -> 25.65 | N12: =product(M12,Variables!$B$5) -> 7.695
B13: Grape | C13: =product(E13,3) -> 56918.376 | D13: =product(E13,1.8) -> 34151.026 | E13: =product('Crop Data'!B8,'Crop Data'!C8,if($I$2="Baseline",1,'Crop Data'!D8),$E$2,Variables!$B$2,Variables!$B$3) -> 18972.792 | F13: =product(product('Crop Data'!B8,$E$2,Variables!$B$2,Variables!$B$3),0.001) -> 26.22 | G13: =product(F13,'Crop Data'!F8) -> 15.732 | I13: Sunflower Silage | J13: =product(L13,3) -> 16138.98 | K13: =product(L13,1.8) -> 9683.388 | L13: =product('Silage Data'!B8,'Silage Data'!C8,$E$2,Variables!$B$2,Variables!$B$3,Variables!$B$4) -> 5379.66 | M13: =product(product('Silage Data'!B8,'Silage Data'!C8,$E$2,Variables!$B$2,Variables!$B$3),0.001) -> 44.46 | N13: =product(M13,Variables!$B$5) -> 13.338
B14: Green Bean | C14: =product(E14,3) -> 22542.502 | D14: =product(E14,1.8) -> 13525.502 | E14: =product('Crop Data'!B9,'Crop Data'!C9,if($I$2="Baseline",1,'Crop Data'!D9),$E$2,Variables!$B$2,Variables!$B$3) -> 7514.1675 | F14: =product(product('Crop Data'!B9,$E$2,Variables!$B$2,Variables!$B$3),0.001) -> 9.939375 | G14: =product(F14,'Crop Data'!F9) -> 4.1745375 | I14: Wheat Silage | J14: =product(L14,3) -> 18414.99 | K14: =product(L14,1.8) -> 11048.994 | L14: =product('Silage Data'!B9,'Silage Data'!C9,$E$2,Variables!$B$2,Variables!$B$3,Variables!$B$4) -> 6138.33 | M14: =product(product('Silage Data'!B9,'Silage Data'!C9,$E$2,Variables!$B$2,Variables!$B$3),0.001) -> 50.73 | N14: =product(M14,Variables!$B$5) -> 15.219
B15: Oat | C15: =product(E15,3) -> 15685.847 | D15: =product(E15,1.8) -> 9411.5083 | E15: =product('Crop Data'!B10,'Crop Data'!C10,if($I$2="Baseline",1,'Crop Data'!D10),$E$2,Variables!$B$2,Variables!$B$3) -> 5228.6157 | F15: 5 | G15: =product(F15,'Crop Data'!F10) -> 2.5 | I15: Grass Silage | J15: =product(L15,3) -> 22604.917 | K15: =product(L15,1.8) -> 13562.951 | L15: =product('Silage Data'!B10,'Silage Data'!C10,$E$2,Variables!$B$2,Variables!$B$3,Variables!$B$4) -> 7534.9725 | M15: =product(product('Silage Data'!B10,'Silage Data'!C10,$E$2,Variables!$B$2,Variables!$B$3),0.001) -> 62.2725 | N15: =product(M15,Variables!$B$5) -> 18.68175
B16: Olive | C16: =product(E16,3) -> 56918.376 | D16: =product(E16,1.8) -> 34151.026 | E16: =product('Crop Data'!B11,'Crop Data'!C11,if($I$2="Baseline",1,'Crop Data'!D11),$E$2,Variables!$B$2,Variables!$B$3) -> 18972.792 | F16: =product(product('Crop Data'!B11,$E$2,Variables!$B$2,Variables!$B$3),0.001) -> 26.22 | G16: =product(F16,'Crop Data'!F11) -> 15.732 | I16: Grass Silage 2x | J16: =product(L16,3) -> 45209.835 | K16: =product(L16,1.8) -> 27125.901 | L16: =product(L15,2) -> 15069.945 | M16: =product(M15,2) -> 124.545 | N16: =product(N15,2) -> 37.3635
B17: Parsnip | C17: =product(E17,3) -> 44759.998 | D17: =product(E17,1.8) -> 26855.999 | E17: =product('Crop Data'!B12,'Crop Data'!C12,if($I$2="Baseline",1,'Crop Data'!D12),$E$2,Variables!$B$2,Variables!$B$3) -> 14919.999 | F17: =product(product('Crop Data'!B12,$E$2,Variables!$B$2,Variables!$B$3),0.001) -> 99.0375 | G17: =product(F17,'Crop Data'!F12) -> 57.44175 | I17: Grass Silage 3x | J17: =product(L17,3) -> 67814.753 | K17: =product(L17,1.8) -> 40688.851 | L17: =product(L15,3) -> 22604.917 | M17: =product(M15,3) -> 186.8175 | N17: =product(N15,3) -> 56.04525
B18: Pea | C18: =product(E18,3) -> 46949.76 | D18: =product(E18,1.8) -> 28169.856 | E18: =product('Crop Data'!B13,'Crop Data'!C13,if($I$2="Baseline",1,'Crop Data'!D13),$E$2,Variables!$B$2,Variables!$B$3) -> 15649.92 | F18: =product(product('Crop Data'!B13,$E$2,Variables!$B$2,Variables!$B$3),0.001) -> 13.68 | G18: =product(F18,'Crop Data'!F13) -> 9.8496 | I18: Grass Silage 4x | J18: =product(L18,3) -> 90419.67 | K18: =product(L18,1.8) -> 54251.802 | L18: =product(L15,4) -> 30139.89 | M18: =product(M15,4) -> 249.09 | N18: =product(N15,4) -> 74.727
B19: Potato | C19: =product(E19,3) -> 45075.13 | D19: =product(E19,1.8) -> 27045.078 | E19: =product('Crop Data'!B14,'Crop Data'!C14,if($I$2="Baseline",1,'Crop Data'!D14),$E$2,Variables!$B$2,Variables!$B$3) -> 15025.043 | F19: =product(product('Crop Data'!B14,$E$2,Variables!$B$2,Variables!$B$3),0.001) -> 58.8525 | G19: =product(F19,'Crop Data'!F14) -> 44.139375 | I19: Poplar (Woodchips) | J19: =product(L19,3) -> 459632.82 | K19: =product(L19,1.8) -> 275779.69 | L19: =product('Crop Data'!B25,'Crop Data'!C25,if($I$2="Baseline",1,'Crop Data'!D25),$E$2,Variables!$B$2,Variables!$B$3) -> 153210.94 | M19: =product(product('Crop Data'!B25,$E$2,Variables!$B$2,Variables!$B$3),0.001) -> 283.30425 | N19: =product(M19,'Crop Data'!F25) -> 99.156487
B20: Rice (Long) | C20: =product(E20,3) -> 21411.338 | D20: =product(E20,1.8) -> 12846.802 | E20: =product('Crop Data'!B15,'Crop Data'!C15,if($I$2="Baseline",1,'Crop Data'!D16),$E$2,Variables!$B$2,Variables!$B$3) -> 7137.1125 | F20: =product(product('Crop Data'!B15,$E$2,Variables!$B$2,Variables!$B$3),0.001) -> 12.825 | G20: =product(F20,'Crop Data'!F15) -> 9.87525
B21: Rice (Short) | C21: =product(E21,3) -> 32588.325 | D21: =product(E21,1.8) -> 19552.995 | E21: =product('Crop Data'!B16,'Crop Data'!C16,if($I$2="Baseline",1,'Crop Data'!D15),$E$2,Variables!$B$2,Variables!$B$3) -> 10862.775 | F21: =product(product('Crop Data'!B16,$E$2,Variables!$B$2,Variables!$B$3),0.001) -> 9.405 | G21: =product(F21,'Crop Data'!F16) -> 7.42995 | I21: NOTES
B22: Sorghum | C22: =product(E22,3) -> 18389.853 | D22: =product(E22,1.8) -> 11033.912 | E22: =product('Crop Data'!B17,'Crop Data'!C17,if($I$2="Baseline",1,'Crop Data'!D17),$E$2,Variables!$B$2,Variables!$B$3) -> 6129.951 | F22: =product(product('Crop Data'!B17,$E$2,Variables!$B$2,Variables!$B$3),0.001) -> 11.685 | G22: =product(F22,'Crop Data'!F17) -> 9.93225 | I22: This does not account for using mods.
B23: Soybean | C23: =product(E23,3) -> 23797.172 | D23: =product(E23,1.8) -> 14278.303 | E23: =product('Crop Data'!B18,'Crop Data'!C18,if($I$2="Baseline",1,'Crop Data'!D18),$E$2,Variables!$B$2,Variables!$B$3) -> 7932.3907 | F23: =product(product('Crop Data'!B18,$E$2,Variables!$B$2,Variables!$B$3),0.001) -> 6.4125 | G23: =product(F23,'Crop Data'!F18) -> 4.48875 | I23: This does not account for how many hours of work are required to grow, harvest, transport and sell your crops. *
B24: Spinach | C24: =product(E24,3) -> 22811.827 | D24: =product(E24,1.8) -> 13687.096 | E24: =product('Crop Data'!B19,'Crop Data'!C19,if($I$2="Baseline",1,'Crop Data'!D19),$E$2,Variables!$B$2,Variables!$B$3) -> 7603.9425 | F24: =product(product('Crop Data'!B19,$E$2,Variables!$B$2,Variables!$B$3),0.001) -> 32.9175 | G24: =product(F24,'Crop Data'!F19) -> 4.279275 | I24: --* (That would require extensive testing and would vary based on the skill of the driver etc.. If someone wants to do this testing, please let me know.)
B25: Sugarbeet | C25: =product(E25,3) -> 48875.391 | D25: =product(E25,1.8) -> 29325.235 | E25: =product('Crop Data'!B20,'Crop Data'!C20,if($I$2="Baseline",1,'Crop Data'!D20),$E$2,Variables!$B$2,Variables!$B$3) -> 16291.797 | F25: =product(product('Crop Data'!B20,$E$2,Variables!$B$2,Variables!$B$3),0.001) -> 82.365 | G25: =product(F25,'Crop Data'!F20) -> 57.6555 | I25: There are myriad other costs and factors not taken in to account here that can affect your gameplay and outcomes.
B26: Sugarcane | C26: =product(E26,3) -> 60573.886 | D26: =product(E26,1.8) -> 36344.331 | E26: =product('Crop Data'!B21,'Crop Data'!C21,if($I$2="Baseline",1,'Crop Data'!D21),$E$2,Variables!$B$2,Variables!$B$3) -> 20191.295 | F26: =product(product('Crop Data'!B21,$E$2,Variables!$B$2,Variables!$B$3),0.001) -> 161.595 | G26: =product(F26,'Crop Data'!F21) -> 29.0871 | I26: M³ means meters cubed, aka cubic meters, the same as 1000 Liters. This is the unit listed for tipper trailer capacity in game.
B27: Sunflower | C27: =product(E27,3) -> 17952.948 | D27: =product(E27,1.8) -> 10771.769 | E27: =product('Crop Data'!B22,'Crop Data'!C22,if($I$2="Baseline",1,'Crop Data'!D22),$E$2,Variables!$B$2,Variables!$B$3) -> 5984.316 | F27: =product(product('Crop Data'!B22,$E$2,Variables!$B$2,Variables!$B$3),0.001) -> 7.41 | G27: =product(F27,'Crop Data'!F22) -> 2.5935 | I27: The poplar figures assume a forage harvester when harvesting poplar woodchips which gives a 3x multiplier to the base yield.
B28: Wheat | C28: =product(E28,3) -> 15514.629 | D28: =product(E28,1.8) -> 9308.7774 | E28: =product('Crop Data'!B23,'Crop Data'!C23,if($I$2="Baseline",1,'Crop Data'!D23),$E$2,Variables!$B$2,Variables!$B$3) -> 5171.543 | F28: =product(product('Crop Data'!B23,$E$2,Variables!$B$2,Variables!$B$3),0.001) -> 12.6825 | G28: =product(F28,'Crop Data'!F23) -> 9.89235 | I28: This does not account for added value from production chains. There is already a tool for that.
B29: Grass | C29: =product(E29,3) -> 9331.5341 | D29: =product(E29,1.8) -> 5598.9205 | E29: =product('Crop Data'!B24,'Crop Data'!C24,if($I$2="Baseline",1,'Crop Data'!D24),$E$2,Variables!$B$2,Variables!$B$3) -> 3110.5114 | F29: =product(product('Crop Data'!B24,$E$2,Variables!$B$2,Variables!$B$3),0.001) -> 62.2725 | G29: =product(F29,'Crop Data'!F24) -> 18.68175 | I29: Just because poplar has a base yield of 6.627 per square meter in the game files, doesn't mean you'll plant it that densely, or that this will be your real yield.
B30: Grass 2x | C30: =product(E30,3) -> 18663.068 | D30: =product(E30,1.8) -> 11197.841 | E30: =product(E29,2) -> 6221.0228 | F30: =product(F29,2) -> 124.545 | G30: =product(G29,2) -> 37.3635 | I30: This does not account for seed costs. Most seed costs are generally low, in the $25 to $150 per acre range, but not all crops are seeded.
B31: Grass 3x | C31: =product(E31,3) -> 27994.602 | D31: =product(E31,1.8) -> 16796.761 | E31: =product(E29,3) -> 9331.5341 | F31: =product(F29,3) -> 186.8175 | G31: =product(G29,3) -> 56.04525 | I31: The prices you see are generally the amount of money you can expect to make, per acre, per harvest, assuming you harvest one acre once per year, but you may harvest more or less often than that.
B32: Grass 4x | C32: =product(E32,3) -> 37326.137 | D32: =product(E32,1.8) -> 22395.682 | E32: =product(E29,4) -> 12442.046 | F32: =product(F29,4) -> 249.09 | G32: =product(G29,4) -> 74.727 | I32: This only generally considers the standard seasons based gameplay such that most crops may only be harvested once per year.
B33: Spinach 2x | C33: =product(E33,3) -> 45623.655 | D33: =product(E33,1.8) -> 27374.193 | E33: =product(E24,2) -> 15207.885 | F33: =product(F24,2) -> 65.835 | G33: =product(G24,2) -> 8.55855 | I33: Some crops like grass and spinach may be harvested multiple times per year, but this also increases your amount of work per year.
I34: Silage price stays the same, unlike crop prices which change on a monthly basis. Crop price fluctuation is fixed, it will follow the same pattern every year.
I35: The Baseline price is approximately the average selling price, with a scalar value of one.
I36: The Max Seasonal price uses the maximum yearly price. This varies per crop. This assumes you can store your grain and wait to sell it until the price it at its maximum.
I37: You can easily still end up getting less money than baseline if you sell at a lower than average seasonal price.
I38: You get a yield bonus for fertilizing, liming, weeding, etc., your exact bonus is likely to vary. Yield bonus goes up to +100% in the base game but only +25% with Precision Farming.
I39: Easy, normal and hard represent the economic difficulty settings of the same names.
I40: This data comes from the official, unaltered, base game data XML files for Farming Simulator 25.
I41: LICENSE
I42: This work is contributed into the public domain. You may copy, share or do anything you want with this, without giving the author credit. By using this work, you do so at your own risk, and you agree to release the author from all liability for any damages arising from or relating to your use of this work.

Sheet Crop Data
A1: NAME | B1: YIELD | C1: PRICE | D1: MAX_PRICE | E1: SEED | F1: WEIGHT
A2: Barley | B2: 0.96 | C2: 0.313 | D2: 1.21 | E2: 0.0265 | F2: 0.68
A3: Beet Root | B3: 5.78 | C3: 0.122 | D3: 1.15 | E3: 0.004 | F3: 0.52
A4: Canola | B4: 0.58 | C4: 0.603 | D4: 1.21 | E4: 0.0049 | F4: 0.6
A5: Carrot | B5: 7.7 | C5: 0.132 | D5: 1.15 | E5: 0.001 | F5: 0.64
A6: Corn | B6: 0.92 | C6: 0.38 | D6: 1.33 | E6: 0.0053 | F6: 0.8
A7: Cotton | B7: 0.497 | C7: 1.252 | D7: 1.11 | E7: 0.005 | F7: 0.23
A8: Grape | B8: 1.84 | C8: 0.603 | D8: 1.2 | E8: 0 | F8: 0.6
A9: Green Bean | B9: 0.6975 | C9: 0.72 | D9: 1.05 | E9: 0.028 | F9: 0.42
A10: Oat | B10: 0.57 | C10: 0.532 | D10: 1.21 | E10: 0.034 | F10: 0.5
A11: Olive | B11: 1.84 | C11: 0.603 | D11: 1.2 | E11: 0 | F11: 0.6
A12: Parsnip | B12: 6.95 | C12: 0.131 | D12: 1.15 | E12: 0.001 | F12: 0.58
A13: Pea | B13: 0.96 | C13: 1.04 | D13: 1.1 | E13: 0.025 | F13: 0.72
... A25: Poplar (Woodchips) | B25: 19.881 | C25: 0.32 | D25: 1.69 | E25: 0.15 | F25: 0.35

Sheet Silage Data
A1: NAME | B1: YIELD | C1: CHAFF
A2: Barley | B2: 0.96 | C2: 4
A3: Canola | B3: 0.58 | C3: 4
A4: Corn | B4: 0.92 | C4: 7.8
A5: Oat | B5: 0.57 | C5: 4
A6: Sorghum | B6: 0.82 | C6: 4
A7: Soybean | B7: 0.45 | C7: 4
A8: Sunflower | B8: 0.52 | C8: 6
A9: Wheat | B9: 0.89 | C9: 4
A10: Grass | B10: 4.37 | C10: 1
A11: Poplar | B11: 6.627 | C11: 3

Sheet Variables
A1: NAME | B1: VALUE
A2: Unit Multiplier | B2: =if(Main!C2="Per Acre", 4046.856, 10000) -> 10000
A3: Yield With Bonus | B3: =sum(1,Main!G2) -> 1.425
A4: Silage Price | B4: 0.121
A5: Chaff Weight | B5: 0.3
A6: Seed Price | B6: =divide(1260,1000) -> 1.26
A7: Grass Weight | B7: 0.3
